pyvpp/WekeoDownload.py
pyvpp/__init__.py
pyvpp-0.3.1.dist-info/METADATA
pyvpp-0.3.1.dist-info/WHEEL
pyvpp-0.3.1.dist-info/licenses/LICENSE
pyvpp-0.3.1.dist-info/RECORD
