Metadata-Version: 2.4
Name: pyvpp
Version: 0.3.1
Summary: Python package to download phenological data from Wekeo (HR-VPP datasets from Sentinel 2)
License: MIT
License-File: LICENSE
Keywords: phenology,hrvpp,vegetation indexes,copernicus,wekeo
Author: Diego García Díaz
Author-email: digd.geografo@gmail.com
Maintainer: Diego García Díaz
Maintainer-email: digd.geografo@gmail.com
Requires-Python: >=3.8,<4.0
Classifier: License :: OSI Approved :: MIT License
Classifier: Programming Language :: Python :: 3
Classifier: Programming Language :: Python :: 3.8
Classifier: Programming Language :: Python :: 3.9
Classifier: Programming Language :: Python :: 3.10
Classifier: Programming Language :: Python :: 3.11
Classifier: Programming Language :: Python :: 3.12
Classifier: Programming Language :: Python :: 3.13
Classifier: Programming Language :: Python :: 3.14
Provides-Extra: dev
Requires-Dist: deims (>=4.0)
Requires-Dist: fiona (>=1.8.20)
Requires-Dist: geopandas (>=0.8.2)
Requires-Dist: hda (>=2.18)
Requires-Dist: pyproj (>=3.0)
Requires-Dist: rasterio (>=1.3)
Requires-Dist: requests (>=2.20)
Project-URL: Repository, https://github.com/Digdgeo/PyVPP
